Metadata-Version: 1.2
Name: pypacker27
Version: 4.2
Summary: Pypacker: The fast and simple packet creating and parsing module
Home-page: https://github.com/mike01/pypacker/tree/python27
Author: Michael Stahn
Author-email: michael.stahn.42@gmail.com
License: BSD
Platform: UNKNOWN
Classifier: Development Status :: 6 - Mature
Classifier: Intended Audience :: Developers
Classifier: License :: OSI Approved :: BSD License
Classifier: Natural Language :: English
Classifier: Programming Language :: Python :: 2.7
Classifier: Programming Language :: Python :: 3.6
Classifier: Programming Language :: Python :: Implementation :: CPython
Classifier: Programming Language :: Python :: Implementation :: PyPy
Requires-Python: >=2.7
